lightnet/__init__.py
lightnet/_compat.py
lightnet/_imports.py
lightnet/_log.py
lightnet/_version.py
lightnet/data/__init__.py
lightnet/data/_dataloading.py
lightnet/data/transform/__init__.py
lightnet/data/transform/_compose.py
lightnet/data/transform/post/__init__.py
lightnet/data/transform/post/_anchor_masked.py
lightnet/data/transform/post/_anchor_oriented.py
lightnet/data/transform/post/_anchor_yolo.py
lightnet/data/transform/post/_base.py
lightnet/data/transform/post/_brambox.py
lightnet/data/transform/post/_corner.py
lightnet/data/transform/post/_nms.py
lightnet/data/transform/post/_reverse_fit.py
lightnet/data/transform/pre/__init__.py
lightnet/data/transform/pre/_augment.py
lightnet/data/transform/pre/_base.py
lightnet/data/transform/pre/_fit.py
lightnet/engine/__init__.py
lightnet/engine/_engine.py
lightnet/engine/_parameter.py
lightnet/engine/_scheduler.py
lightnet/models/__init__.py
lightnet/models/_dataset_brambox.py
lightnet/models/_dataset_darknet.py
lightnet/models/_network_alexnet.py
lightnet/models/_network_cornernet.py
lightnet/models/_network_cornernet_squeeze.py
lightnet/models/_network_cspdarknet53.py
lightnet/models/_network_darknet.py
lightnet/models/_network_darknet19.py
lightnet/models/_network_darknet53.py
lightnet/models/_network_dyolo.py
lightnet/models/_network_mobile_darknet19.py
lightnet/models/_network_mobile_yolo_v2.py
lightnet/models/_network_mobile_yolo_v2_upsample.py
lightnet/models/_network_mobilenet_v1.py
lightnet/models/_network_mobilenet_v2.py
lightnet/models/_network_mobilenet_yolo.py
lightnet/models/_network_resnet.py
lightnet/models/_network_resnet_yolo.py
lightnet/models/_network_tiny_yolo_v2.py
lightnet/models/_network_tiny_yolo_v3.py
lightnet/models/_network_vgg.py
lightnet/models/_network_yolact.py
lightnet/models/_network_yolo_fusion.py
lightnet/models/_network_yolo_v2.py
lightnet/models/_network_yolo_v2_upsample.py
lightnet/models/_network_yolo_v3.py
lightnet/models/_network_yolo_v4.py
lightnet-4.0.0.dist-info/LICENSE
lightnet-4.0.0.dist-info/METADATA
lightnet-4.0.0.dist-info/WHEEL
lightnet-4.0.0.dist-info/top_level.txt
lightnet-4.0.0.dist-info/RECORD
