Metadata-Version: 2.1
Name: lightnet
Version: 4.0.0
Summary: Building blocks for recreating darknet networks in pytorch
Author: EAVISE
License-File: LICENSE
Requires-Dist: numpy
Requires-Dist: torch
Requires-Dist: torchvision
Requires-Dist: packaging
Requires-Dist: pandas
Provides-Extra: segment
Requires-Dist: pgpd >=2 ; extra == 'segment'
Requires-Dist: brambox >=3.3 ; extra == 'segment'
Provides-Extra: training
Requires-Dist: brambox >=2 ; extra == 'training'
Requires-Dist: scikit-learn ; extra == 'training'
